{
  "href": "https://api.spotify.com/v1/albums/11cpAynoDMZFD0B2xtw6OQ/tracks?offset=0&limit=50",
  "items": [
    {
      "artists": [
        {
          "external_urls": {
            "spotify": "https://open.spotify.com/artist/4tZwfgrHOc3mvqYlEYSvVi"
          },
          "href": "https://api.spotify.com/v1/artists/4tZwfgrHOc3mvqYlEYSvVi",
          "id": "4tZwfgrHOc3mvqYlEYSvVi",
          "name": "Daft Punk",
          "type": "artist",
          "uri": "spotify:artist:4tZwfgrHOc3mvqYlEYSvVi"
        },
        {
          "external_urls": {
            "spotify": "https://open.spotify.com/artist/43mWhBXSflupNLuNjM5vff"
          },
          "href": "https://api.spotify.com/v1/artists/43mWhBXSflupNLuNjM5vff",
          "id": "43mWhBXSflupNLuNjM5vff",
          "name": "Soulwax",
          "type": "artist",
          "uri": "spotify:artist:43mWhBXSflupNLuNjM5vff"
        }
      ],
      "disc_number": 1,
      "duration_ms": 390506,
      "explicit": false,
      "external_urls": {
        "spotify": "https://open.spotify.com/track/0BEDdX7TWPEt1gWnbVbHdN"
      },
      "href": "https://api.spotify.com/v1/tracks/0BEDdX7TWPEt1gWnbVbHdN",
      "id": "0BEDdX7TWPEt1gWnbVbHdN",
      "name": "Robot Rock - Soulwax Remix",
      "track_number": 1,
      "type": "track",
      "uri": "spotify:track:0BEDdX7TWPEt1gWnbVbHdN",
      "is_local": false
    },
    {
      "artists": [
        {
          "external_urls": {
            "spotify": "https://open.spotify.com/artist/4tZwfgrHOc3mvqYlEYSvVi"
          },
          "href": "https://api.spotify.com/v1/artists/4tZwfgrHOc3mvqYlEYSvVi",
          "id": "4tZwfgrHOc3mvqYlEYSvVi",
          "name": "Daft Punk",
          "type": "artist",
          "uri": "spotify:artist:4tZwfgrHOc3mvqYlEYSvVi"
        },
        {
          "external_urls": {
            "spotify": "https://open.spotify.com/artist/5tOWIviwLM1EIqGAbF8VSU"
          },
          "href": "https://api.spotify.com/v1/artists/5tOWIviwLM1EIqGAbF8VSU",
          "id": "5tOWIviwLM1EIqGAbF8VSU",
          "name": "SebastiAn",
          "type": "artist",
          "uri": "spotify:artist:5tOWIviwLM1EIqGAbF8VSU"
        }
      ],
      "disc_number": 1,
      "duration_ms": 287640,
      "explicit": false,
      "external_urls": {
        "spotify": "https://open.spotify.com/track/4TeYKbvzloWQ1eGG4JB4b6"
      },
      "href": "https://api.spotify.com/v1/tracks/4TeYKbvzloWQ1eGG4JB4b6",
      "id": "4TeYKbvzloWQ1eGG4JB4b6",
      "name": "Human After All - SebastiAn Remix",
      "track_number": 2,
      "type": "track",
      "uri": "spotify:track:4TeYKbvzloWQ1eGG4JB4b6",
      "is_local": false
    },
    {
      "artists": [
        {
          "external_urls": {
            "spotify": "https://open.spotify.com/artist/4tZwfgrHOc3mvqYlEYSvVi"
          },
          "href": "https://api.spotify.com/v1/artists/4tZwfgrHOc3mvqYlEYSvVi",
          "id": "4tZwfgrHOc3mvqYlEYSvVi",
          "name": "Daft Punk",
          "type": "artist",
          "uri": "spotify:artist:4tZwfgrHOc3mvqYlEYSvVi"
        },
        {
          "external_urls": {
            "spotify": "https://open.spotify.com/artist/1gkSl4XpHIHI4I1WQbfXOE"
          },
          "href": "https://api.spotify.com/v1/artists/1gkSl4XpHIHI4I1WQbfXOE",
          "id": "1gkSl4XpHIHI4I1WQbfXOE",
          "name": "Peaches",
          "type": "artist",
          "uri": "spotify:artist:1gkSl4XpHIHI4I1WQbfXOE"
        }
      ],
      "disc_number": 1,
      "duration_ms": 280413,
      "explicit": false,
      "external_urls": {
        "spotify": "https://open.spotify.com/track/6Wn1bfoqAXHqzjoNSzpiKs"
      },
      "href": "https://api.spotify.com/v1/tracks/6Wn1bfoqAXHqzjoNSzpiKs",
      "id": "6Wn1bfoqAXHqzjoNSzpiKs",
      "name": "Technologic - Peaches No Logic Remix",
      "track_number": 3,
      "type": "track",
      "uri": "spotify:track:6Wn1bfoqAXHqzjoNSzpiKs",
      "is_local": false
    },
    {
      "artists": [
        {
          "external_urls": {
            "spotify": "https://open.spotify.com/artist/4tZwfgrHOc3mvqYlEYSvVi"
          },
          "href": "https://api.spotify.com/v1/artists/4tZwfgrHOc3mvqYlEYSvVi",
          "id": "4tZwfgrHOc3mvqYlEYSvVi",
          "name": "Daft Punk",
          "type": "artist",
          "uri": "spotify:artist:4tZwfgrHOc3mvqYlEYSvVi"
        },
        {
          "external_urls": {
            "spotify": "https://open.spotify.com/artist/3jQ8hpdQo3TCEnb5gmOtH5"
          },
          "href": "https://api.spotify.com/v1/artists/3jQ8hpdQo3TCEnb5gmOtH5",
          "id": "3jQ8hpdQo3TCEnb5gmOtH5",
          "name": "Erol Alkan",
          "type": "artist",
          "uri": "spotify:artist:3jQ8hpdQo3TCEnb5gmOtH5"
        }
      ],
      "disc_number": 1,
      "duration_ms": 364040,
      "explicit": false,
      "external_urls": {
        "spotify": "https://open.spotify.com/track/14vpfA3QRbZQNEn7ojtL3Z"
      },
      "href": "https://api.spotify.com/v1/tracks/14vpfA3QRbZQNEn7ojtL3Z",
      "id": "14vpfA3QRbZQNEn7ojtL3Z",
      "name": "Brainwasher - Erol Alkan's Horrorhouse Dub",
      "track_number": 4,
      "type": "track",
      "uri": "spotify:track:14vpfA3QRbZQNEn7ojtL3Z",
      "is_local": false
    },
    {
      "artists": [
        {
          "external_urls": {
            "spotify": "https://open.spotify.com/artist/4tZwfgrHOc3mvqYlEYSvVi"
          },
          "href": "https://api.spotify.com/v1/artists/4tZwfgrHOc3mvqYlEYSvVi",
          "id": "4tZwfgrHOc3mvqYlEYSvVi",
          "name": "Daft Punk",
          "type": "artist",
          "uri": "spotify:artist:4tZwfgrHOc3mvqYlEYSvVi"
        },
        {
          "external_urls": {
            "spotify": "https://open.spotify.com/artist/5MRONaryo2z75lLiuJ0NWJ"
          },
          "href": "https://api.spotify.com/v1/artists/5MRONaryo2z75lLiuJ0NWJ",
          "id": "5MRONaryo2z75lLiuJ0NWJ",
          "name": "Para One",
          "type": "artist",
          "uri": "spotify:artist:5MRONaryo2z75lLiuJ0NWJ"
        }
      ],
      "disc_number": 1,
      "duration_ms": 231560,
      "explicit": false,
      "external_urls": {
        "spotify": "https://open.spotify.com/track/7z04OESfPf9PiaJPX3h5hr"
      },
      "href": "https://api.spotify.com/v1/tracks/7z04OESfPf9PiaJPX3h5hr",
      "id": "7z04OESfPf9PiaJPX3h5hr",
      "name": "Prime Time of Your Life - Para One Remix",
      "track_number": 5,
      "type": "track",
      "uri": "spotify:track:7z04OESfPf9PiaJPX3h5hr",
      "is_local": false
    },
    {
      "artists": [
        {
          "external_urls": {
            "spotify": "https://open.spotify.com/artist/4tZwfgrHOc3mvqYlEYSvVi"
          },
          "href": "https://api.spotify.com/v1/artists/4tZwfgrHOc3mvqYlEYSvVi",
          "id": "4tZwfgrHOc3mvqYlEYSvVi",
          "name": "Daft Punk",
          "type": "artist",
          "uri": "spotify:artist:4tZwfgrHOc3mvqYlEYSvVi"
        },
        {
          "external_urls": {
            "spotify": "https://open.spotify.com/artist/1gR0gsQYfi6joyO1dlp76N"
          },
          "href": "https://api.spotify.com/v1/artists/1gR0gsQYfi6joyO1dlp76N",
          "id": "1gR0gsQYfi6joyO1dlp76N",
          "name": "Justice",
          "type": "artist",
          "uri": "spotify:artist:1gR0gsQYfi6joyO1dlp76N"
        }
      ],
      "disc_number": 1,
      "duration_ms": 240373,
      "explicit": false,
      "external_urls": {
        "spotify": "https://open.spotify.com/track/2QkzakBouxPqiWI7ke3Tso"
      },
      "href": "https://api.spotify.com/v1/tracks/2QkzakBouxPqiWI7ke3Tso",
      "id": "2QkzakBouxPqiWI7ke3Tso",
      "name": "Human After All - \"Guy-Man After All\" Justice Remix",
      "track_number": 6,
      "type": "track",
      "uri": "spotify:track:2QkzakBouxPqiWI7ke3Tso",
      "is_local": false
    },
    {
      "artists": [
        {
          "external_urls": {
            "spotify": "https://open.spotify.com/artist/4tZwfgrHOc3mvqYlEYSvVi"
          },
          "href": "https://api.spotify.com/v1/artists/4tZwfgrHOc3mvqYlEYSvVi",
          "id": "4tZwfgrHOc3mvqYlEYSvVi",
          "name": "Daft Punk",
          "type": "artist",
          "uri": "spotify:artist:4tZwfgrHOc3mvqYlEYSvVi"
        },
        {
          "external_urls": {
            "spotify": "https://open.spotify.com/artist/2fBURuq7FrlH6z5F92mpOl"
          },
          "href": "https://api.spotify.com/v1/artists/2fBURuq7FrlH6z5F92mpOl",
          "id": "2fBURuq7FrlH6z5F92mpOl",
          "name": "Digitalism",
          "type": "artist",
          "uri": "spotify:artist:2fBURuq7FrlH6z5F92mpOl"
        }
      ],
      "disc_number": 1,
      "duration_ms": 361213,
      "explicit": false,
      "external_urls": {
        "spotify": "https://open.spotify.com/track/01sOjRlYusOIfxC9qaSYqQ"
      },
      "href": "https://api.spotify.com/v1/tracks/01sOjRlYusOIfxC9qaSYqQ",
      "id": "01sOjRlYusOIfxC9qaSYqQ",
      "name": "Technologic - Digitalism Remix",
      "track_number": 7,
      "type": "track",
      "uri": "spotify:track:01sOjRlYusOIfxC9qaSYqQ",
      "is_local": false
    },
    {
      "artists": [
        {
          "external_urls": {
            "spotify": "https://open.spotify.com/artist/4tZwfgrHOc3mvqYlEYSvVi"
          },
          "href": "https://api.spotify.com/v1/artists/4tZwfgrHOc3mvqYlEYSvVi",
          "id": "4tZwfgrHOc3mvqYlEYSvVi",
          "name": "Daft Punk",
          "type": "artist",
          "uri": "spotify:artist:4tZwfgrHOc3mvqYlEYSvVi"
        },
        {
          "external_urls": {
            "spotify": "https://open.spotify.com/artist/1bnxrGpNXaVSzgbwEFL0qj"
          },
          "href": "https://api.spotify.com/v1/artists/1bnxrGpNXaVSzgbwEFL0qj",
          "id": "1bnxrGpNXaVSzgbwEFL0qj",
          "name": "Alter Ego",
          "type": "artist",
          "uri": "spotify:artist:1bnxrGpNXaVSzgbwEFL0qj"
        }
      ],
      "disc_number": 1,
      "duration_ms": 565826,
      "explicit": false,
      "external_urls": {
        "spotify": "https://open.spotify.com/track/1wjNeiqNI6gXr8MJgnVIo2"
      },
      "href": "https://api.spotify.com/v1/tracks/1wjNeiqNI6gXr8MJgnVIo2",
      "id": "1wjNeiqNI6gXr8MJgnVIo2",
      "name": "Human After All - Alter Ego Remix",
      "track_number": 8,
      "type": "track",
      "uri": "spotify:track:1wjNeiqNI6gXr8MJgnVIo2",
      "is_local": false
    },
    {
      "artists": [
        {
          "external_urls": {
            "spotify": "https://open.spotify.com/artist/4tZwfgrHOc3mvqYlEYSvVi"
          },
          "href": "https://api.spotify.com/v1/artists/4tZwfgrHOc3mvqYlEYSvVi",
          "id": "4tZwfgrHOc3mvqYlEYSvVi",
          "name": "Daft Punk",
          "type": "artist",
          "uri": "spotify:artist:4tZwfgrHOc3mvqYlEYSvVi"
        },
        {
          "external_urls": {
            "spotify": "https://open.spotify.com/artist/4M84umUNRbZy1mJleyyRM9"
          },
          "href": "https://api.spotify.com/v1/artists/4M84umUNRbZy1mJleyyRM9",
          "id": "4M84umUNRbZy1mJleyyRM9",
          "name": "Vitalic",
          "type": "artist",
          "uri": "spotify:artist:4M84umUNRbZy1mJleyyRM9"
        }
      ],
      "disc_number": 1,
      "duration_ms": 324840,
      "explicit": false,
      "external_urls": {
        "spotify": "https://open.spotify.com/track/1QKWEOrj8Ee8PBu6mPVSw1"
      },
      "href": "https://api.spotify.com/v1/tracks/1QKWEOrj8Ee8PBu6mPVSw1",
      "id": "1QKWEOrj8Ee8PBu6mPVSw1",
      "name": "Technologic - Vitalic Remix",
      "track_number": 9,
      "type": "track",
      "uri": "spotify:track:1QKWEOrj8Ee8PBu6mPVSw1",
      "is_local": false
    },
    {
      "artists": [
        {
          "external_urls": {
            "spotify": "https://open.spotify.com/artist/4tZwfgrHOc3mvqYlEYSvVi"
          },
          "href": "https://api.spotify.com/v1/artists/4tZwfgrHOc3mvqYlEYSvVi",
          "id": "4tZwfgrHOc3mvqYlEYSvVi",
          "name": "Daft Punk",
          "type": "artist",
          "uri": "spotify:artist:4tZwfgrHOc3mvqYlEYSvVi"
        }
      ],
      "disc_number": 1,
      "duration_ms": 355960,
      "explicit": false,
      "external_urls": {
        "spotify": "https://open.spotify.com/track/6QqtrujZQLMtsHiyk9rKyA"
      },
      "href": "https://api.spotify.com/v1/tracks/6QqtrujZQLMtsHiyk9rKyA",
      "id": "6QqtrujZQLMtsHiyk9rKyA",
      "name": "Robot Rock - Maximum Overdrive Mix",
      "track_number": 10,
      "type": "track",
      "uri": "spotify:track:6QqtrujZQLMtsHiyk9rKyA",
      "is_local": false
    },
    {
      "artists": [
        {
          "external_urls": {
            "spotify": "https://open.spotify.com/artist/4tZwfgrHOc3mvqYlEYSvVi"
          },
          "href": "https://api.spotify.com/v1/artists/4tZwfgrHOc3mvqYlEYSvVi",
          "id": "4tZwfgrHOc3mvqYlEYSvVi",
          "name": "Daft Punk",
          "type": "artist",
          "uri": "spotify:artist:4tZwfgrHOc3mvqYlEYSvVi"
        },
        {
          "external_urls": {
            "spotify": "https://open.spotify.com/artist/6fJLczsevKaRi1D8zX7vRJ"
          },
          "href": "https://api.spotify.com/v1/artists/6fJLczsevKaRi1D8zX7vRJ",
          "id": "6fJLczsevKaRi1D8zX7vRJ",
          "name": "Liquid Twins",
          "type": "artist",
          "uri": "spotify:artist:6fJLczsevKaRi1D8zX7vRJ"
        }
      ],
      "disc_number": 1,
      "duration_ms": 250573,
      "explicit": false,
      "external_urls": {
        "spotify": "https://open.spotify.com/track/11L5sMCBeor1mFUW0cXrIR"
      },
      "href": "https://api.spotify.com/v1/tracks/11L5sMCBeor1mFUW0cXrIR",
      "id": "11L5sMCBeor1mFUW0cXrIR",
      "name": "Technologic - Liquid Twins Remix",
      "track_number": 11,
      "type": "track",
      "uri": "spotify:track:11L5sMCBeor1mFUW0cXrIR",
      "is_local": false
    },
    {
      "artists": [
        {
          "external_urls": {
            "spotify": "https://open.spotify.com/artist/4tZwfgrHOc3mvqYlEYSvVi"
          },
          "href": "https://api.spotify.com/v1/artists/4tZwfgrHOc3mvqYlEYSvVi",
          "id": "4tZwfgrHOc3mvqYlEYSvVi",
          "name": "Daft Punk",
          "type": "artist",
          "uri": "spotify:artist:4tZwfgrHOc3mvqYlEYSvVi"
        },
        {
          "external_urls": {
            "spotify": "https://open.spotify.com/artist/4YrKBkKSVeqDamzBPWVnSJ"
          },
          "href": "https://api.spotify.com/v1/artists/4YrKBkKSVeqDamzBPWVnSJ",
          "id": "4YrKBkKSVeqDamzBPWVnSJ",
          "name": "Basement Jaxx",
          "type": "artist",
          "uri": "spotify:artist:4YrKBkKSVeqDamzBPWVnSJ"
        }
      ],
      "disc_number": 1,
      "duration_ms": 331693,
      "explicit": false,
      "external_urls": {
        "spotify": "https://open.spotify.com/track/6RZRao7yG0G50VRvu3M4ct"
      },
      "href": "https://api.spotify.com/v1/tracks/6RZRao7yG0G50VRvu3M4ct",
      "id": "6RZRao7yG0G50VRvu3M4ct",
      "name": "Technologic - Basement Jaxx Kontrol Mixx",
      "track_number": 12,
      "type": "track",
      "uri": "spotify:track:6RZRao7yG0G50VRvu3M4ct",
      "is_local": false
    },
    {
      "artists": [
        {
          "external_urls": {
            "spotify": "https://open.spotify.com/artist/4tZwfgrHOc3mvqYlEYSvVi"
          },
          "href": "https://api.spotify.com/v1/artists/4tZwfgrHOc3mvqYlEYSvVi",
          "id": "4tZwfgrHOc3mvqYlEYSvVi",
          "name": "Daft Punk",
          "type": "artist",
          "uri": "spotify:artist:4tZwfgrHOc3mvqYlEYSvVi"
        },
        {
          "external_urls": {
            "spotify": "https://open.spotify.com/artist/7gG6LkU3pCSQmCIPR4aSBt"
          },
          "href": "https://api.spotify.com/v1/artists/7gG6LkU3pCSQmCIPR4aSBt",
          "id": "7gG6LkU3pCSQmCIPR4aSBt",
          "name": "The Juan Maclean",
          "type": "artist",
          "uri": "spotify:artist:7gG6LkU3pCSQmCIPR4aSBt"
        }
      ],
      "disc_number": 1,
      "duration_ms": 403026,
      "explicit": false,
      "external_urls": {
        "spotify": "https://open.spotify.com/track/7v7NHYIzIs9anGBUFFMamf"
      },
      "href": "https://api.spotify.com/v1/tracks/7v7NHYIzIs9anGBUFFMamf",
      "id": "7v7NHYIzIs9anGBUFFMamf",
      "name": "Human After All - The Juan Mclean Remix",
      "track_number": 13,
      "type": "track",
      "uri": "spotify:track:7v7NHYIzIs9anGBUFFMamf",
      "is_local": false
    },
    {
      "artists": [
        {
          "external_urls": {
            "spotify": "https://open.spotify.com/artist/4tZwfgrHOc3mvqYlEYSvVi"
          },
          "href": "https://api.spotify.com/v1/artists/4tZwfgrHOc3mvqYlEYSvVi",
          "id": "4tZwfgrHOc3mvqYlEYSvVi",
          "name": "Daft Punk",
          "type": "artist",
          "uri": "spotify:artist:4tZwfgrHOc3mvqYlEYSvVi"
        },
        {
          "external_urls": {
            "spotify": "https://open.spotify.com/artist/0euaSBwkNAZFqyRcthOIa2"
          },
          "href": "https://api.spotify.com/v1/artists/0euaSBwkNAZFqyRcthOIa2",
          "id": "0euaSBwkNAZFqyRcthOIa2",
          "name": "Emperor Machine",
          "type": "artist",
          "uri": "spotify:artist:0euaSBwkNAZFqyRcthOIa2"
        }
      ],
      "disc_number": 1,
      "duration_ms": 363946,
      "explicit": false,
      "external_urls": {
        "spotify": "https://open.spotify.com/track/0frwUWLdF1PnPF4ysjlBA4"
      },
      "href": "https://api.spotify.com/v1/tracks/0frwUWLdF1PnPF4ysjlBA4",
      "id": "0frwUWLdF1PnPF4ysjlBA4",
      "name": "Human After All - Emperor Machine Version",
      "track_number": 14,
      "type": "track",
      "uri": "spotify:track:0frwUWLdF1PnPF4ysjlBA4",
      "is_local": false
    },
    {
      "artists": [
        {
          "external_urls": {
            "spotify": "https://open.spotify.com/artist/4tZwfgrHOc3mvqYlEYSvVi"
          },
          "href": "https://api.spotify.com/v1/artists/4tZwfgrHOc3mvqYlEYSvVi",
          "id": "4tZwfgrHOc3mvqYlEYSvVi",
          "name": "Daft Punk",
          "type": "artist",
          "uri": "spotify:artist:4tZwfgrHOc3mvqYlEYSvVi"
        },
        {
          "external_urls": {
            "spotify": "https://open.spotify.com/artist/46C7zcoy351lNv6pMTStN9"
          },
          "href": "https://api.spotify.com/v1/artists/46C7zcoy351lNv6pMTStN9",
          "id": "46C7zcoy351lNv6pMTStN9",
          "name": "Le Knight Club",
          "type": "artist",
          "uri": "spotify:artist:46C7zcoy351lNv6pMTStN9"
        }
      ],
      "disc_number": 1,
      "duration_ms": 328093,
      "explicit": false,
      "external_urls": {
        "spotify": "https://open.spotify.com/track/5b3n32izrzbkTMC16FZ83r"
      },
      "href": "https://api.spotify.com/v1/tracks/5b3n32izrzbkTMC16FZ83r",
      "id": "5b3n32izrzbkTMC16FZ83r",
      "name": "Technologic - Le Knight Club Remix",
      "track_number": 15,
      "type": "track",
      "uri": "spotify:track:5b3n32izrzbkTMC16FZ83r",
      "is_local": false
    }
  ],
  "limit": 50,
  "next": null,
  "offset": 0,
  "previous": null,
  "total": 15
}