[
  {
    "artists": [
      {
        "external_urls": {
          "spotify": "https://open.spotify.com/artist/2wUjUUtkb5lvLKcGKsKqsR"
        },
        "href": "https://api.spotify.com/v1/artists/2wUjUUtkb5lvLKcGKsKqsR",
        "id": "2wUjUUtkb5lvLKcGKsKqsR",
        "name": "Alessia Cara",
        "type": "artist",
        "uri": "spotify:artist:2wUjUUtkb5lvLKcGKsKqsR"
      }
    ],
    "disc_number": 1,
    "duration_ms": 230240,
    "explicit": false,
    "external_urls": {
      "spotify": "https://open.spotify.com/track/76LaUv3TqnONpncShGwpcx"
    },
    "href": "https://api.spotify.com/v1/tracks/76LaUv3TqnONpncShGwpcx",
    "id": "76LaUv3TqnONpncShGwpcx",
    "name": "Scars To Your Beautiful",
    "track_number": 1,
    "type": "track",
    "uri": "spotify:track:76LaUv3TqnONpncShGwpcx",
    "is_local": false
  },
  {
    "artists": [
      {
        "external_urls": {
          "spotify": "https://open.spotify.com/artist/6jJ0s89eD6GaHleKKya26X"
        },
        "href": "https://api.spotify.com/v1/artists/6jJ0s89eD6GaHleKKya26X",
        "id": "6jJ0s89eD6GaHleKKya26X",
        "name": "Katy Perry",
        "type": "artist",
        "uri": "spotify:artist:6jJ0s89eD6GaHleKKya26X"
      }
    ],
    "disc_number": 1,
    "duration_ms": 220226,
    "explicit": false,
    "external_urls": {
      "spotify": "https://open.spotify.com/track/4YvLq9PWChQViYHp6deLiR"
    },
    "href": "https://api.spotify.com/v1/tracks/4YvLq9PWChQViYHp6deLiR",
    "id": "4YvLq9PWChQViYHp6deLiR",
    "name": "Hot N Cold",
    "track_number": 2,
    "type": "track",
    "uri": "spotify:track:4YvLq9PWChQViYHp6deLiR",
    "is_local": false
  },
  {
    "artists": [
      {
        "external_urls": {
          "spotify": "https://open.spotify.com/artist/6qqNVTkY8uBg9cP3Jd7DAH"
        },
        "href": "https://api.spotify.com/v1/artists/6qqNVTkY8uBg9cP3Jd7DAH",
        "id": "6qqNVTkY8uBg9cP3Jd7DAH",
        "name": "Billie Eilish",
        "type": "artist",
        "uri": "spotify:artist:6qqNVTkY8uBg9cP3Jd7DAH"
      }
    ],
    "disc_number": 1,
    "duration_ms": 174321,
    "explicit": false,
    "external_urls": {
      "spotify": "https://open.spotify.com/track/4elGhp3Qba6E5EWE8mssmm"
    },
    "href": "https://api.spotify.com/v1/tracks/4elGhp3Qba6E5EWE8mssmm",
    "id": "4elGhp3Qba6E5EWE8mssmm",
    "name": "Therefore I Am",
    "track_number": 3,
    "type": "track",
    "uri": "spotify:track:4elGhp3Qba6E5EWE8mssmm",
    "is_local": false
  },
  {
    "artists": [
      {
        "external_urls": {
          "spotify": "https://open.spotify.com/artist/06HL4z0CvFAxyc27GXpf02"
        },
        "href": "https://api.spotify.com/v1/artists/06HL4z0CvFAxyc27GXpf02",
        "id": "06HL4z0CvFAxyc27GXpf02",
        "name": "Taylor Swift",
        "type": "artist",
        "uri": "spotify:artist:06HL4z0CvFAxyc27GXpf02"
      }
    ],
    "disc_number": 1,
    "duration_ms": 231124,
    "explicit": false,
    "external_urls": {
      "spotify": "https://open.spotify.com/track/0tjakmOR0E24e8uwVVAhka"
    },
    "href": "https://api.spotify.com/v1/tracks/0tjakmOR0E24e8uwVVAhka",
    "id": "0tjakmOR0E24e8uwVVAhka",
    "name": "You Belong With Me (Taylor’s Version)",
    "track_number": 4,
    "type": "track",
    "uri": "spotify:track:0tjakmOR0E24e8uwVVAhka",
    "is_local": false
  },
  {
    "artists": [
      {
        "external_urls": {
          "spotify": "https://open.spotify.com/artist/5p7f24Rk5HkUZsaS3BLG5F"
        },
        "href": "https://api.spotify.com/v1/artists/5p7f24Rk5HkUZsaS3BLG5F",
        "id": "5p7f24Rk5HkUZsaS3BLG5F",
        "name": "Hailee Steinfeld",
        "type": "artist",
        "uri": "spotify:artist:5p7f24Rk5HkUZsaS3BLG5F"
      }
    ],
    "disc_number": 1,
    "duration_ms": 220520,
    "explicit": false,
    "external_urls": {
      "spotify": "https://open.spotify.com/track/6tS2IUijne5F0xt8biMyVb"
    },
    "href": "https://api.spotify.com/v1/tracks/6tS2IUijne5F0xt8biMyVb",
    "id": "6tS2IUijne5F0xt8biMyVb",
    "name": "Love Myself",
    "track_number": 5,
    "type": "track",
    "uri": "spotify:track:6tS2IUijne5F0xt8biMyVb",
    "is_local": false
  },
  {
    "artists": [
      {
        "external_urls": {
          "spotify": "https://open.spotify.com/artist/79AyR6ATpj2LTPxfb6FX50"
        },
        "href": "https://api.spotify.com/v1/artists/79AyR6ATpj2LTPxfb6FX50",
        "id": "79AyR6ATpj2LTPxfb6FX50",
        "name": "Lauren Spencer Smith",
        "type": "artist",
        "uri": "spotify:artist:79AyR6ATpj2LTPxfb6FX50"
      }
    ],
    "disc_number": 1,
    "duration_ms": 175344,
    "explicit": false,
    "external_urls": {
      "spotify": "https://open.spotify.com/track/2ZWLxNirK7uYBbOiPGxqgy"
    },
    "href": "https://api.spotify.com/v1/tracks/2ZWLxNirK7uYBbOiPGxqgy",
    "id": "2ZWLxNirK7uYBbOiPGxqgy",
    "name": "Fingers Crossed",
    "track_number": 6,
    "type": "track",
    "uri": "spotify:track:2ZWLxNirK7uYBbOiPGxqgy",
    "is_local": false
  },
  {
    "artists": [
      {
        "external_urls": {
          "spotify": "https://open.spotify.com/artist/5e4Dhzv426EvQe3aDb64jL"
        },
        "href": "https://api.spotify.com/v1/artists/5e4Dhzv426EvQe3aDb64jL",
        "id": "5e4Dhzv426EvQe3aDb64jL",
        "name": "Shania Twain",
        "type": "artist",
        "uri": "spotify:artist:5e4Dhzv426EvQe3aDb64jL"
      }
    ],
    "disc_number": 1,
    "duration_ms": 233000,
    "explicit": false,
    "external_urls": {
      "spotify": "https://open.spotify.com/track/6XjBW1M2j2UX222eBF8wB6"
    },
    "href": "https://api.spotify.com/v1/tracks/6XjBW1M2j2UX222eBF8wB6",
    "id": "6XjBW1M2j2UX222eBF8wB6",
    "name": "Man! I Feel Like A Woman!",
    "track_number": 7,
    "type": "track",
    "uri": "spotify:track:6XjBW1M2j2UX222eBF8wB6",
    "is_local": false
  },
  {
    "artists": [
      {
        "external_urls": {
          "spotify": "https://open.spotify.com/artist/1McMsnEElThX1knmY4oliG"
        },
        "href": "https://api.spotify.com/v1/artists/1McMsnEElThX1knmY4oliG",
        "id": "1McMsnEElThX1knmY4oliG",
        "name": "Olivia Rodrigo",
        "type": "artist",
        "uri": "spotify:artist:1McMsnEElThX1knmY4oliG"
      }
    ],
    "disc_number": 1,
    "duration_ms": 178147,
    "explicit": true,
    "external_urls": {
      "spotify": "https://open.spotify.com/track/2twc0ZBAzXEsd0AwChOXMW"
    },
    "href": "https://api.spotify.com/v1/tracks/2twc0ZBAzXEsd0AwChOXMW",
    "id": "2twc0ZBAzXEsd0AwChOXMW",
    "name": "good 4 u",
    "track_number": 8,
    "type": "track",
    "uri": "spotify:track:2twc0ZBAzXEsd0AwChOXMW",
    "is_local": false
  },
  {
    "artists": [
      {
        "external_urls": {
          "spotify": "https://open.spotify.com/artist/1U1el3k54VvEUzo3ybLPlM"
        },
        "href": "https://api.spotify.com/v1/artists/1U1el3k54VvEUzo3ybLPlM",
        "id": "1U1el3k54VvEUzo3ybLPlM",
        "name": "Kali Uchis",
        "type": "artist",
        "uri": "spotify:artist:1U1el3k54VvEUzo3ybLPlM"
      }
    ],
    "disc_number": 1,
    "duration_ms": 160191,
    "explicit": false,
    "external_urls": {
      "spotify": "https://open.spotify.com/track/6uIQEjXtxFcHBV0lBDY8V6"
    },
    "href": "https://api.spotify.com/v1/tracks/6uIQEjXtxFcHBV0lBDY8V6",
    "id": "6uIQEjXtxFcHBV0lBDY8V6",
    "name": "telepatía",
    "track_number": 9,
    "type": "track",
    "uri": "spotify:track:6uIQEjXtxFcHBV0lBDY8V6",
    "is_local": false
  },
  {
    "artists": [
      {
        "external_urls": {
          "spotify": "https://open.spotify.com/artist/0uq5PttqEjj3IH1bzwcrXF"
        },
        "href": "https://api.spotify.com/v1/artists/0uq5PttqEjj3IH1bzwcrXF",
        "id": "0uq5PttqEjj3IH1bzwcrXF",
        "name": "Spice Girls",
        "type": "artist",
        "uri": "spotify:artist:0uq5PttqEjj3IH1bzwcrXF"
      }
    ],
    "disc_number": 1,
    "duration_ms": 237933,
    "explicit": false,
    "external_urls": {
      "spotify": "https://open.spotify.com/track/2Y31xemwMDrxEvmGpK7t11"
    },
    "href": "https://api.spotify.com/v1/tracks/2Y31xemwMDrxEvmGpK7t11",
    "id": "2Y31xemwMDrxEvmGpK7t11",
    "name": "Say You'll Be There",
    "track_number": 10,
    "type": "track",
    "uri": "spotify:track:2Y31xemwMDrxEvmGpK7t11",
    "is_local": false
  },
  {
    "artists": [
      {
        "external_urls": {
          "spotify": "https://open.spotify.com/artist/4yiQZ8tQPux8cPriYMWUFP"
        },
        "href": "https://api.spotify.com/v1/artists/4yiQZ8tQPux8cPriYMWUFP",
        "id": "4yiQZ8tQPux8cPriYMWUFP",
        "name": "Gwen Stefani",
        "type": "artist",
        "uri": "spotify:artist:4yiQZ8tQPux8cPriYMWUFP"
      }
    ],
    "disc_number": 1,
    "duration_ms": 199853,
    "explicit": true,
    "external_urls": {
      "spotify": "https://open.spotify.com/track/0HxCzgpiejSu5D9xRtuh6a"
    },
    "href": "https://api.spotify.com/v1/tracks/0HxCzgpiejSu5D9xRtuh6a",
    "id": "0HxCzgpiejSu5D9xRtuh6a",
    "name": "Hollaback Girl",
    "track_number": 11,
    "type": "track",
    "uri": "spotify:track:0HxCzgpiejSu5D9xRtuh6a",
    "is_local": false
  },
  {
    "artists": [
      {
        "external_urls": {
          "spotify": "https://open.spotify.com/artist/57bUPid8xztkieZfS7OlEV"
        },
        "href": "https://api.spotify.com/v1/artists/57bUPid8xztkieZfS7OlEV",
        "id": "57bUPid8xztkieZfS7OlEV",
        "name": "The Supremes",
        "type": "artist",
        "uri": "spotify:artist:57bUPid8xztkieZfS7OlEV"
      }
    ],
    "disc_number": 1,
    "duration_ms": 181786,
    "explicit": false,
    "external_urls": {
      "spotify": "https://open.spotify.com/track/1wtPIe94xtUQR95D7zEi8F"
    },
    "href": "https://api.spotify.com/v1/tracks/1wtPIe94xtUQR95D7zEi8F",
    "id": "1wtPIe94xtUQR95D7zEi8F",
    "name": "You Can't Hurry Love",
    "track_number": 12,
    "type": "track",
    "uri": "spotify:track:1wtPIe94xtUQR95D7zEi8F",
    "is_local": false
  },
  {
    "artists": [
      {
        "external_urls": {
          "spotify": "https://open.spotify.com/artist/4xFUf1FHVy696Q1JQZMTRj"
        },
        "href": "https://api.spotify.com/v1/artists/4xFUf1FHVy696Q1JQZMTRj",
        "id": "4xFUf1FHVy696Q1JQZMTRj",
        "name": "Carrie Underwood",
        "type": "artist",
        "uri": "spotify:artist:4xFUf1FHVy696Q1JQZMTRj"
      }
    ],
    "disc_number": 1,
    "duration_ms": 202853,
    "explicit": false,
    "external_urls": {
      "spotify": "https://open.spotify.com/track/5urvPwSxKgQbrtH8R7Jjk0"
    },
    "href": "https://api.spotify.com/v1/tracks/5urvPwSxKgQbrtH8R7Jjk0",
    "id": "5urvPwSxKgQbrtH8R7Jjk0",
    "name": "Southbound",
    "track_number": 13,
    "type": "track",
    "uri": "spotify:track:5urvPwSxKgQbrtH8R7Jjk0",
    "is_local": false
  },
  {
    "artists": [
      {
        "external_urls": {
          "spotify": "https://open.spotify.com/artist/5p7f24Rk5HkUZsaS3BLG5F"
        },
        "href": "https://api.spotify.com/v1/artists/5p7f24Rk5HkUZsaS3BLG5F",
        "id": "5p7f24Rk5HkUZsaS3BLG5F",
        "name": "Hailee Steinfeld",
        "type": "artist",
        "uri": "spotify:artist:5p7f24Rk5HkUZsaS3BLG5F"
      }
    ],
    "disc_number": 1,
    "duration_ms": 204400,
    "explicit": false,
    "external_urls": {
      "spotify": "https://open.spotify.com/track/1OGaIp7sefHR9UMkDJJkmP"
    },
    "href": "https://api.spotify.com/v1/tracks/1OGaIp7sefHR9UMkDJJkmP",
    "id": "1OGaIp7sefHR9UMkDJJkmP",
    "name": "Most Girls",
    "track_number": 14,
    "type": "track",
    "uri": "spotify:track:1OGaIp7sefHR9UMkDJJkmP",
    "is_local": false
  },
  {
    "artists": [
      {
        "external_urls": {
          "spotify": "https://open.spotify.com/artist/43mhFhQ4JAknA7Ik1bOZuV"
        },
        "href": "https://api.spotify.com/v1/artists/43mhFhQ4JAknA7Ik1bOZuV",
        "id": "43mhFhQ4JAknA7Ik1bOZuV",
        "name": "Pat Benatar",
        "type": "artist",
        "uri": "spotify:artist:43mhFhQ4JAknA7Ik1bOZuV"
      }
    ],
    "disc_number": 1,
    "duration_ms": 172133,
    "explicit": false,
    "external_urls": {
      "spotify": "https://open.spotify.com/track/5KavxFWf8SNgvLQ5TrB0q3"
    },
    "href": "https://api.spotify.com/v1/tracks/5KavxFWf8SNgvLQ5TrB0q3",
    "id": "5KavxFWf8SNgvLQ5TrB0q3",
    "name": "Hit Me With Your Best Shot",
    "track_number": 15,
    "type": "track",
    "uri": "spotify:track:5KavxFWf8SNgvLQ5TrB0q3",
    "is_local": false
  },
  {
    "artists": [
      {
        "external_urls": {
          "spotify": "https://open.spotify.com/artist/1HY2Jd0NmPuamShAr6KMms"
        },
        "href": "https://api.spotify.com/v1/artists/1HY2Jd0NmPuamShAr6KMms",
        "id": "1HY2Jd0NmPuamShAr6KMms",
        "name": "Lady Gaga",
        "type": "artist",
        "uri": "spotify:artist:1HY2Jd0NmPuamShAr6KMms"
      }
    ],
    "disc_number": 1,
    "duration_ms": 320626,
    "explicit": false,
    "external_urls": {
      "spotify": "https://open.spotify.com/track/3MyIZvfVWDxHzDG9VsIgD8"
    },
    "href": "https://api.spotify.com/v1/tracks/3MyIZvfVWDxHzDG9VsIgD8",
    "id": "3MyIZvfVWDxHzDG9VsIgD8",
    "name": "The Edge Of Glory",
    "track_number": 16,
    "type": "track",
    "uri": "spotify:track:3MyIZvfVWDxHzDG9VsIgD8",
    "is_local": false
  },
  {
    "artists": [
      {
        "external_urls": {
          "spotify": "https://open.spotify.com/artist/0aqrM7Fo3Ml66Kc5JAzmjt"
        },
        "href": "https://api.spotify.com/v1/artists/0aqrM7Fo3Ml66Kc5JAzmjt",
        "id": "0aqrM7Fo3Ml66Kc5JAzmjt",
        "name": "Deana Carter",
        "type": "artist",
        "uri": "spotify:artist:0aqrM7Fo3Ml66Kc5JAzmjt"
      }
    ],
    "disc_number": 1,
    "duration_ms": 291533,
    "explicit": false,
    "external_urls": {
      "spotify": "https://open.spotify.com/track/7Kc6SoW2hjSfEs1uiqcPyu"
    },
    "href": "https://api.spotify.com/v1/tracks/7Kc6SoW2hjSfEs1uiqcPyu",
    "id": "7Kc6SoW2hjSfEs1uiqcPyu",
    "name": "Strawberry Wine",
    "track_number": 17,
    "type": "track",
    "uri": "spotify:track:7Kc6SoW2hjSfEs1uiqcPyu",
    "is_local": false
  },
  {
    "artists": [
      {
        "external_urls": {
          "spotify": "https://open.spotify.com/artist/1eEfMU2AhEo7XnKgL7c304"
        },
        "href": "https://api.spotify.com/v1/artists/1eEfMU2AhEo7XnKgL7c304",
        "id": "1eEfMU2AhEo7XnKgL7c304",
        "name": "Carpenters",
        "type": "artist",
        "uri": "spotify:artist:1eEfMU2AhEo7XnKgL7c304"
      }
    ],
    "disc_number": 1,
    "duration_ms": 271287,
    "explicit": false,
    "external_urls": {
      "spotify": "https://open.spotify.com/track/2lDTN6bAWuuXr2QXnBgF6q"
    },
    "href": "https://api.spotify.com/v1/tracks/2lDTN6bAWuuXr2QXnBgF6q",
    "id": "2lDTN6bAWuuXr2QXnBgF6q",
    "name": "(They Long To Be) Close To You",
    "track_number": 18,
    "type": "track",
    "uri": "spotify:track:2lDTN6bAWuuXr2QXnBgF6q",
    "is_local": false
  },
  {
    "artists": [
      {
        "external_urls": {
          "spotify": "https://open.spotify.com/artist/75L9s8KVrhCNtBUkZFnDFW"
        },
        "href": "https://api.spotify.com/v1/artists/75L9s8KVrhCNtBUkZFnDFW",
        "id": "75L9s8KVrhCNtBUkZFnDFW",
        "name": "Vanessa Williams",
        "type": "artist",
        "uri": "spotify:artist:75L9s8KVrhCNtBUkZFnDFW"
      }
    ],
    "disc_number": 1,
    "duration_ms": 219760,
    "explicit": false,
    "external_urls": {
      "spotify": "https://open.spotify.com/track/3b9nO19Ome6VCeP3gWYhPS"
    },
    "href": "https://api.spotify.com/v1/tracks/3b9nO19Ome6VCeP3gWYhPS",
    "id": "3b9nO19Ome6VCeP3gWYhPS",
    "name": "Save The Best For Last",
    "track_number": 19,
    "type": "track",
    "uri": "spotify:track:3b9nO19Ome6VCeP3gWYhPS",
    "is_local": false
  },
  {
    "artists": [
      {
        "external_urls": {
          "spotify": "https://open.spotify.com/artist/4yiQZ8tQPux8cPriYMWUFP"
        },
        "href": "https://api.spotify.com/v1/artists/4yiQZ8tQPux8cPriYMWUFP",
        "id": "4yiQZ8tQPux8cPriYMWUFP",
        "name": "Gwen Stefani",
        "type": "artist",
        "uri": "spotify:artist:4yiQZ8tQPux8cPriYMWUFP"
      }
    ],
    "disc_number": 1,
    "duration_ms": 223586,
    "explicit": false,
    "external_urls": {
      "spotify": "https://open.spotify.com/track/2LpGR1U99XtnLs2iPhFyzJ"
    },
    "href": "https://api.spotify.com/v1/tracks/2LpGR1U99XtnLs2iPhFyzJ",
    "id": "2LpGR1U99XtnLs2iPhFyzJ",
    "name": "What You Waiting For?",
    "track_number": 20,
    "type": "track",
    "uri": "spotify:track:2LpGR1U99XtnLs2iPhFyzJ",
    "is_local": false
  },
  {
    "artists": [
      {
        "external_urls": {
          "spotify": "https://open.spotify.com/artist/6qqNVTkY8uBg9cP3Jd7DAH"
        },
        "href": "https://api.spotify.com/v1/artists/6qqNVTkY8uBg9cP3Jd7DAH",
        "id": "6qqNVTkY8uBg9cP3Jd7DAH",
        "name": "Billie Eilish",
        "type": "artist",
        "uri": "spotify:artist:6qqNVTkY8uBg9cP3Jd7DAH"
      }
    ],
    "disc_number": 1,
    "duration_ms": 245425,
    "explicit": false,
    "external_urls": {
      "spotify": "https://open.spotify.com/track/5PvKLysp5qWA09JWWdVWdq"
    },
    "href": "https://api.spotify.com/v1/tracks/5PvKLysp5qWA09JWWdVWdq",
    "id": "5PvKLysp5qWA09JWWdVWdq",
    "name": "everything i wanted",
    "track_number": 21,
    "type": "track",
    "uri": "spotify:track:5PvKLysp5qWA09JWWdVWdq",
    "is_local": false
  },
  {
    "artists": [
      {
        "external_urls": {
          "spotify": "https://open.spotify.com/artist/4NHQUGzhtTLFvgF5SZesLK"
        },
        "href": "https://api.spotify.com/v1/artists/4NHQUGzhtTLFvgF5SZesLK",
        "id": "4NHQUGzhtTLFvgF5SZesLK",
        "name": "Tove Lo",
        "type": "artist",
        "uri": "spotify:artist:4NHQUGzhtTLFvgF5SZesLK"
      }
    ],
    "disc_number": 1,
    "duration_ms": 199179,
    "explicit": true,
    "external_urls": {
      "spotify": "https://open.spotify.com/track/7eVOpzWnj0ZqhpMPIjitUx"
    },
    "href": "https://api.spotify.com/v1/tracks/7eVOpzWnj0ZqhpMPIjitUx",
    "id": "7eVOpzWnj0ZqhpMPIjitUx",
    "name": "Cool Girl",
    "track_number": 22,
    "type": "track",
    "uri": "spotify:track:7eVOpzWnj0ZqhpMPIjitUx",
    "is_local": false
  },
  {
    "artists": [
      {
        "external_urls": {
          "spotify": "https://open.spotify.com/artist/7o2ZQYM7nTsaVdkXY38UAA"
        },
        "href": "https://api.spotify.com/v1/artists/7o2ZQYM7nTsaVdkXY38UAA",
        "id": "7o2ZQYM7nTsaVdkXY38UAA",
        "name": "Em Beihold",
        "type": "artist",
        "uri": "spotify:artist:7o2ZQYM7nTsaVdkXY38UAA"
      }
    ],
    "disc_number": 1,
    "duration_ms": 169237,
    "explicit": false,
    "external_urls": {
      "spotify": "https://open.spotify.com/track/6Cri5JVdztbREQj8XecO9G"
    },
    "href": "https://api.spotify.com/v1/tracks/6Cri5JVdztbREQj8XecO9G",
    "id": "6Cri5JVdztbREQj8XecO9G",
    "name": "Numb Little Bug",
    "track_number": 23,
    "type": "track",
    "uri": "spotify:track:6Cri5JVdztbREQj8XecO9G",
    "is_local": false
  },
  {
    "artists": [
      {
        "external_urls": {
          "spotify": "https://open.spotify.com/artist/6oWOHAOyBUn6aJlKIPJK9r"
        },
        "href": "https://api.spotify.com/v1/artists/6oWOHAOyBUn6aJlKIPJK9r",
        "id": "6oWOHAOyBUn6aJlKIPJK9r",
        "name": "Leah Kate",
        "type": "artist",
        "uri": "spotify:artist:6oWOHAOyBUn6aJlKIPJK9r"
      }
    ],
    "disc_number": 1,
    "duration_ms": 157138,
    "explicit": true,
    "external_urls": {
      "spotify": "https://open.spotify.com/track/4aGcbw7AMuqYMGmd0NWcHy"
    },
    "href": "https://api.spotify.com/v1/tracks/4aGcbw7AMuqYMGmd0NWcHy",
    "id": "4aGcbw7AMuqYMGmd0NWcHy",
    "name": "10 Things I Hate About You",
    "track_number": 24,
    "type": "track",
    "uri": "spotify:track:4aGcbw7AMuqYMGmd0NWcHy",
    "is_local": false
  },
  {
    "artists": [
      {
        "external_urls": {
          "spotify": "https://open.spotify.com/artist/0LcJLqbBmaGUft1e9Mm8HV"
        },
        "href": "https://api.spotify.com/v1/artists/0LcJLqbBmaGUft1e9Mm8HV",
        "id": "0LcJLqbBmaGUft1e9Mm8HV",
        "name": "ABBA",
        "type": "artist",
        "uri": "spotify:artist:0LcJLqbBmaGUft1e9Mm8HV"
      }
    ],
    "disc_number": 1,
    "duration_ms": 231093,
    "explicit": false,
    "external_urls": {
      "spotify": "https://open.spotify.com/track/2yNglOCFpVrZwgOAIjjsns"
    },
    "href": "https://api.spotify.com/v1/tracks/2yNglOCFpVrZwgOAIjjsns",
    "id": "2yNglOCFpVrZwgOAIjjsns",
    "name": "Dancing Queen",
    "track_number": 25,
    "type": "track",
    "uri": "spotify:track:2yNglOCFpVrZwgOAIjjsns",
    "is_local": false
  },
  {
    "artists": [
      {
        "external_urls": {
          "spotify": "https://open.spotify.com/artist/0ZED1XzwlLHW4ZaG4lOT6m"
        },
        "href": "https://api.spotify.com/v1/artists/0ZED1XzwlLHW4ZaG4lOT6m",
        "id": "0ZED1XzwlLHW4ZaG4lOT6m",
        "name": "Julia Michaels",
        "type": "artist",
        "uri": "spotify:artist:0ZED1XzwlLHW4ZaG4lOT6m"
      },
      {
        "external_urls": {
          "spotify": "https://open.spotify.com/artist/1Hsdzj7Dlq2I7tHP7501T4"
        },
        "href": "https://api.spotify.com/v1/artists/1Hsdzj7Dlq2I7tHP7501T4",
        "id": "1Hsdzj7Dlq2I7tHP7501T4",
        "name": "Niall Horan",
        "type": "artist",
        "uri": "spotify:artist:1Hsdzj7Dlq2I7tHP7501T4"
      }
    ],
    "disc_number": 1,
    "duration_ms": 173306,
    "explicit": false,
    "external_urls": {
      "spotify": "https://open.spotify.com/track/3IYCbvJestYuoJUCpE4HBT"
    },
    "href": "https://api.spotify.com/v1/tracks/3IYCbvJestYuoJUCpE4HBT",
    "id": "3IYCbvJestYuoJUCpE4HBT",
    "name": "What A Time",
    "track_number": 26,
    "type": "track",
    "uri": "spotify:track:3IYCbvJestYuoJUCpE4HBT",
    "is_local": false
  },
  {
    "artists": [
      {
        "external_urls": {
          "spotify": "https://open.spotify.com/artist/6jJ0s89eD6GaHleKKya26X"
        },
        "href": "https://api.spotify.com/v1/artists/6jJ0s89eD6GaHleKKya26X",
        "id": "6jJ0s89eD6GaHleKKya26X",
        "name": "Katy Perry",
        "type": "artist",
        "uri": "spotify:artist:6jJ0s89eD6GaHleKKya26X"
      }
    ],
    "disc_number": 1,
    "duration_ms": 222666,
    "explicit": false,
    "external_urls": {
      "spotify": "https://open.spotify.com/track/0j0nbbI3FHE9GlsZJ6M7vw"
    },
    "href": "https://api.spotify.com/v1/tracks/0j0nbbI3FHE9GlsZJ6M7vw",
    "id": "0j0nbbI3FHE9GlsZJ6M7vw",
    "name": "Roar",
    "track_number": 27,
    "type": "track",
    "uri": "spotify:track:0j0nbbI3FHE9GlsZJ6M7vw",
    "is_local": false
  }
]