[
  {
    "artists": [
      {
        "external_urls": {
          "spotify": "https://open.spotify.com/artist/790FomKkXshlbRYZFtlgla"
        },
        "href": "https://api.spotify.com/v1/artists/790FomKkXshlbRYZFtlgla",
        "id": "790FomKkXshlbRYZFtlgla",
        "name": "KAROL G",
        "type": "artist",
        "uri": "spotify:artist:790FomKkXshlbRYZFtlgla"
      }
    ],
    "disc_number": 1,
    "duration_ms": 178346,
    "explicit": false,
    "external_urls": {
      "spotify": "https://open.spotify.com/track/2wfOHqHEZKUGKiXdx6QUmn"
    },
    "href": "https://api.spotify.com/v1/tracks/2wfOHqHEZKUGKiXdx6QUmn",
    "id": "2wfOHqHEZKUGKiXdx6QUmn",
    "name": "Pineapple",
    "track_number": 1,
    "type": "track",
    "uri": "spotify:track:2wfOHqHEZKUGKiXdx6QUmn",
    "is_local": false
  },
  {
    "artists": [
      {
        "external_urls": {
          "spotify": "https://open.spotify.com/artist/2wY79sveU1sp5g7SokKOiI"
        },
        "href": "https://api.spotify.com/v1/artists/2wY79sveU1sp5g7SokKOiI",
        "id": "2wY79sveU1sp5g7SokKOiI",
        "name": "Sam Smith",
        "type": "artist",
        "uri": "spotify:artist:2wY79sveU1sp5g7SokKOiI"
      }
    ],
    "disc_number": 1,
    "duration_ms": 162732,
    "explicit": false,
    "external_urls": {
      "spotify": "https://open.spotify.com/track/1mWlfv7zLyN7WxSFALVCnF"
    },
    "href": "https://api.spotify.com/v1/tracks/1mWlfv7zLyN7WxSFALVCnF",
    "id": "1mWlfv7zLyN7WxSFALVCnF",
    "name": "Make It To Me",
    "track_number": 2,
    "type": "track",
    "uri": "spotify:track:1mWlfv7zLyN7WxSFALVCnF",
    "is_local": false
  },
  {
    "artists": [
      {
        "external_urls": {
          "spotify": "https://open.spotify.com/artist/1l9d7B8W0IHy3LqWsxP2SH"
        },
        "href": "https://api.spotify.com/v1/artists/1l9d7B8W0IHy3LqWsxP2SH",
        "id": "1l9d7B8W0IHy3LqWsxP2SH",
        "name": "Phantogram",
        "type": "artist",
        "uri": "spotify:artist:1l9d7B8W0IHy3LqWsxP2SH"
      },
      {
        "external_urls": {
          "spotify": "https://open.spotify.com/artist/4kBCXTJBl1aY9pDHONsjfr"
        },
        "href": "https://api.spotify.com/v1/artists/4kBCXTJBl1aY9pDHONsjfr",
        "id": "4kBCXTJBl1aY9pDHONsjfr",
        "name": "xxtristanxo",
        "type": "artist",
        "uri": "spotify:artist:4kBCXTJBl1aY9pDHONsjfr"
      },
      {
        "external_urls": {
          "spotify": "https://open.spotify.com/artist/7zmcKgBZSbMxqzqFe6Ac5k"
        },
        "href": "https://api.spotify.com/v1/artists/7zmcKgBZSbMxqzqFe6Ac5k",
        "id": "7zmcKgBZSbMxqzqFe6Ac5k",
        "name": "Slowed Radio",
        "type": "artist",
        "uri": "spotify:artist:7zmcKgBZSbMxqzqFe6Ac5k"
      },
      {
        "external_urls": {
          "spotify": "https://open.spotify.com/artist/1WvvwcQx0tj6NdDhZZ2zZz"
        },
        "href": "https://api.spotify.com/v1/artists/1WvvwcQx0tj6NdDhZZ2zZz",
        "id": "1WvvwcQx0tj6NdDhZZ2zZz",
        "name": "Future Islands",
        "type": "artist",
        "uri": "spotify:artist:1WvvwcQx0tj6NdDhZZ2zZz"
      }
    ],
    "disc_number": 1,
    "duration_ms": 214394,
    "explicit": false,
    "external_urls": {
      "spotify": "https://open.spotify.com/track/6kUm26VrB3MwgA8HYRD4jK"
    },
    "href": "https://api.spotify.com/v1/tracks/6kUm26VrB3MwgA8HYRD4jK",
    "id": "6kUm26VrB3MwgA8HYRD4jK",
    "name": "Black Out Days - Future Islands Remix (Slowed)",
    "track_number": 3,
    "type": "track",
    "uri": "spotify:track:6kUm26VrB3MwgA8HYRD4jK",
    "is_local": false
  },
  {
    "artists": [
      {
        "external_urls": {
          "spotify": "https://open.spotify.com/artist/0LcJLqbBmaGUft1e9Mm8HV"
        },
        "href": "https://api.spotify.com/v1/artists/0LcJLqbBmaGUft1e9Mm8HV",
        "id": "0LcJLqbBmaGUft1e9Mm8HV",
        "name": "ABBA",
        "type": "artist",
        "uri": "spotify:artist:0LcJLqbBmaGUft1e9Mm8HV"
      }
    ],
    "disc_number": 1,
    "duration_ms": 289160,
    "explicit": false,
    "external_urls": {
      "spotify": "https://open.spotify.com/track/4eJVq1dx4E5u2XDcJC0kjm"
    },
    "href": "https://api.spotify.com/v1/tracks/4eJVq1dx4E5u2XDcJC0kjm",
    "id": "4eJVq1dx4E5u2XDcJC0kjm",
    "name": "Gimme! Gimme! Gimme! (A Man After Midnight)",
    "track_number": 4,
    "type": "track",
    "uri": "spotify:track:4eJVq1dx4E5u2XDcJC0kjm",
    "is_local": false
  },
  {
    "artists": [
      {
        "external_urls": {
          "spotify": "https://open.spotify.com/artist/1lmU3giNF3CSbkVSQmLpHQ"
        },
        "href": "https://api.spotify.com/v1/artists/1lmU3giNF3CSbkVSQmLpHQ",
        "id": "1lmU3giNF3CSbkVSQmLpHQ",
        "name": "Surf Mesa",
        "type": "artist",
        "uri": "spotify:artist:1lmU3giNF3CSbkVSQmLpHQ"
      },
      {
        "external_urls": {
          "spotify": "https://open.spotify.com/artist/2kRfqPViCqYdSGhYSM9R0Q"
        },
        "href": "https://api.spotify.com/v1/artists/2kRfqPViCqYdSGhYSM9R0Q",
        "id": "2kRfqPViCqYdSGhYSM9R0Q",
        "name": "Madison Beer",
        "type": "artist",
        "uri": "spotify:artist:2kRfqPViCqYdSGhYSM9R0Q"
      }
    ],
    "disc_number": 1,
    "duration_ms": 182653,
    "explicit": false,
    "external_urls": {
      "spotify": "https://open.spotify.com/track/2kSx6OL7PCNX7qypWuvppD"
    },
    "href": "https://api.spotify.com/v1/tracks/2kSx6OL7PCNX7qypWuvppD",
    "id": "2kSx6OL7PCNX7qypWuvppD",
    "name": "Carried Away (Love To Love)",
    "track_number": 5,
    "type": "track",
    "uri": "spotify:track:2kSx6OL7PCNX7qypWuvppD",
    "is_local": false
  },
  {
    "artists": [
      {
        "external_urls": {
          "spotify": "https://open.spotify.com/artist/70kkdajctXSbqSMJbQO424"
        },
        "href": "https://api.spotify.com/v1/artists/70kkdajctXSbqSMJbQO424",
        "id": "70kkdajctXSbqSMJbQO424",
        "name": "Kacey Musgraves",
        "type": "artist",
        "uri": "spotify:artist:70kkdajctXSbqSMJbQO424"
      }
    ],
    "disc_number": 1,
    "duration_ms": 180800,
    "explicit": false,
    "external_urls": {
      "spotify": "https://open.spotify.com/track/57BhMUMPuYJKcWd34e1Btr"
    },
    "href": "https://api.spotify.com/v1/tracks/57BhMUMPuYJKcWd34e1Btr",
    "id": "57BhMUMPuYJKcWd34e1Btr",
    "name": "justified",
    "track_number": 6,
    "type": "track",
    "uri": "spotify:track:57BhMUMPuYJKcWd34e1Btr",
    "is_local": false
  },
  {
    "artists": [
      {
        "external_urls": {
          "spotify": "https://open.spotify.com/artist/1WaFQSHVGZQJTbf0BdxdNo"
        },
        "href": "https://api.spotify.com/v1/artists/1WaFQSHVGZQJTbf0BdxdNo",
        "id": "1WaFQSHVGZQJTbf0BdxdNo",
        "name": "Tommy Richman",
        "type": "artist",
        "uri": "spotify:artist:1WaFQSHVGZQJTbf0BdxdNo"
      }
    ],
    "disc_number": 1,
    "duration_ms": 148800,
    "explicit": true,
    "external_urls": {
      "spotify": "https://open.spotify.com/track/2DK7Bkp5pDC9vuwBRq7F7o"
    },
    "href": "https://api.spotify.com/v1/tracks/2DK7Bkp5pDC9vuwBRq7F7o",
    "id": "2DK7Bkp5pDC9vuwBRq7F7o",
    "name": "Chrono Trigger",
    "track_number": 7,
    "type": "track",
    "uri": "spotify:track:2DK7Bkp5pDC9vuwBRq7F7o",
    "is_local": false
  },
  {
    "artists": [
      {
        "external_urls": {
          "spotify": "https://open.spotify.com/artist/2wY79sveU1sp5g7SokKOiI"
        },
        "href": "https://api.spotify.com/v1/artists/2wY79sveU1sp5g7SokKOiI",
        "id": "2wY79sveU1sp5g7SokKOiI",
        "name": "Sam Smith",
        "type": "artist",
        "uri": "spotify:artist:2wY79sveU1sp5g7SokKOiI"
      }
    ],
    "disc_number": 1,
    "duration_ms": 166346,
    "explicit": false,
    "external_urls": {
      "spotify": "https://open.spotify.com/track/11EN8vUL734hxnyR3tNm7l"
    },
    "href": "https://api.spotify.com/v1/tracks/11EN8vUL734hxnyR3tNm7l",
    "id": "11EN8vUL734hxnyR3tNm7l",
    "name": "Like I Can",
    "track_number": 8,
    "type": "track",
    "uri": "spotify:track:11EN8vUL734hxnyR3tNm7l",
    "is_local": false
  },
  {
    "artists": [
      {
        "external_urls": {
          "spotify": "https://open.spotify.com/artist/0ZED1XzwlLHW4ZaG4lOT6m"
        },
        "href": "https://api.spotify.com/v1/artists/0ZED1XzwlLHW4ZaG4lOT6m",
        "id": "0ZED1XzwlLHW4ZaG4lOT6m",
        "name": "Julia Michaels",
        "type": "artist",
        "uri": "spotify:artist:0ZED1XzwlLHW4ZaG4lOT6m"
      },
      {
        "external_urls": {
          "spotify": "https://open.spotify.com/artist/1Hsdzj7Dlq2I7tHP7501T4"
        },
        "href": "https://api.spotify.com/v1/artists/1Hsdzj7Dlq2I7tHP7501T4",
        "id": "1Hsdzj7Dlq2I7tHP7501T4",
        "name": "Niall Horan",
        "type": "artist",
        "uri": "spotify:artist:1Hsdzj7Dlq2I7tHP7501T4"
      }
    ],
    "disc_number": 1,
    "duration_ms": 173306,
    "explicit": false,
    "external_urls": {
      "spotify": "https://open.spotify.com/track/3p5YEguQamdUL0129v5z2O"
    },
    "href": "https://api.spotify.com/v1/tracks/3p5YEguQamdUL0129v5z2O",
    "id": "3p5YEguQamdUL0129v5z2O",
    "name": "What A Time",
    "track_number": 9,
    "type": "track",
    "uri": "spotify:track:3p5YEguQamdUL0129v5z2O",
    "is_local": false
  },
  {
    "artists": [
      {
        "external_urls": {
          "spotify": "https://open.spotify.com/artist/4NpFxQe2UvRCAjto3JqlSl"
        },
        "href": "https://api.spotify.com/v1/artists/4NpFxQe2UvRCAjto3JqlSl",
        "id": "4NpFxQe2UvRCAjto3JqlSl",
        "name": "Greta Van Fleet",
        "type": "artist",
        "uri": "spotify:artist:4NpFxQe2UvRCAjto3JqlSl"
      }
    ],
    "disc_number": 1,
    "duration_ms": 341255,
    "explicit": false,
    "external_urls": {
      "spotify": "https://open.spotify.com/track/3oXM8RlrTDl8OSQNpiRg7z"
    },
    "href": "https://api.spotify.com/v1/tracks/3oXM8RlrTDl8OSQNpiRg7z",
    "id": "3oXM8RlrTDl8OSQNpiRg7z",
    "name": "Heat Above",
    "track_number": 10,
    "type": "track",
    "uri": "spotify:track:3oXM8RlrTDl8OSQNpiRg7z",
    "is_local": false
  },
  {
    "artists": [
      {
        "external_urls": {
          "spotify": "https://open.spotify.com/artist/76JyRfZDqhAIow2Awv91iW"
        },
        "href": "https://api.spotify.com/v1/artists/76JyRfZDqhAIow2Awv91iW",
        "id": "76JyRfZDqhAIow2Awv91iW",
        "name": "B. Smyth",
        "type": "artist",
        "uri": "spotify:artist:76JyRfZDqhAIow2Awv91iW"
      }
    ],
    "disc_number": 1,
    "duration_ms": 237880,
    "explicit": false,
    "external_urls": {
      "spotify": "https://open.spotify.com/track/3hg3Un2hZNoeSIYTRi7gOA"
    },
    "href": "https://api.spotify.com/v1/tracks/3hg3Un2hZNoeSIYTRi7gOA",
    "id": "3hg3Un2hZNoeSIYTRi7gOA",
    "name": "Twerkoholic",
    "track_number": 11,
    "type": "track",
    "uri": "spotify:track:3hg3Un2hZNoeSIYTRi7gOA",
    "is_local": false
  },
  {
    "artists": [
      {
        "external_urls": {
          "spotify": "https://open.spotify.com/artist/06HL4z0CvFAxyc27GXpf02"
        },
        "href": "https://api.spotify.com/v1/artists/06HL4z0CvFAxyc27GXpf02",
        "id": "06HL4z0CvFAxyc27GXpf02",
        "name": "Taylor Swift",
        "type": "artist",
        "uri": "spotify:artist:06HL4z0CvFAxyc27GXpf02"
      }
    ],
    "disc_number": 1,
    "duration_ms": 221306,
    "explicit": false,
    "external_urls": {
      "spotify": "https://open.spotify.com/track/5b6Gzv20HXMU9BOBPCeOcU"
    },
    "href": "https://api.spotify.com/v1/tracks/5b6Gzv20HXMU9BOBPCeOcU",
    "id": "5b6Gzv20HXMU9BOBPCeOcU",
    "name": "Lover",
    "track_number": 12,
    "type": "track",
    "uri": "spotify:track:5b6Gzv20HXMU9BOBPCeOcU",
    "is_local": false
  },
  {
    "artists": [
      {
        "external_urls": {
          "spotify": "https://open.spotify.com/artist/7blXVKBSxdFZsIqlhdViKc"
        },
        "href": "https://api.spotify.com/v1/artists/7blXVKBSxdFZsIqlhdViKc",
        "id": "7blXVKBSxdFZsIqlhdViKc",
        "name": "Valley",
        "type": "artist",
        "uri": "spotify:artist:7blXVKBSxdFZsIqlhdViKc"
      }
    ],
    "disc_number": 1,
    "duration_ms": 155384,
    "explicit": true,
    "external_urls": {
      "spotify": "https://open.spotify.com/track/1c2vmpc9E1JJMRoKifY2QX"
    },
    "href": "https://api.spotify.com/v1/tracks/1c2vmpc9E1JJMRoKifY2QX",
    "id": "1c2vmpc9E1JJMRoKifY2QX",
    "name": "Oh shit…are we in love?",
    "track_number": 13,
    "type": "track",
    "uri": "spotify:track:1c2vmpc9E1JJMRoKifY2QX",
    "is_local": false
  },
  {
    "artists": [
      {
        "external_urls": {
          "spotify": "https://open.spotify.com/artist/7cxXeGqb1uIhoiSXQ6kejX"
        },
        "href": "https://api.spotify.com/v1/artists/7cxXeGqb1uIhoiSXQ6kejX",
        "id": "7cxXeGqb1uIhoiSXQ6kejX",
        "name": "The Lorax Singers",
        "type": "artist",
        "uri": "spotify:artist:7cxXeGqb1uIhoiSXQ6kejX"
      },
      {
        "external_urls": {
          "spotify": "https://open.spotify.com/artist/47MKT4N2j09fZJ683zjDRk"
        },
        "href": "https://api.spotify.com/v1/artists/47MKT4N2j09fZJ683zjDRk",
        "id": "47MKT4N2j09fZJ683zjDRk",
        "name": "Jenny Slate",
        "type": "artist",
        "uri": "spotify:artist:47MKT4N2j09fZJ683zjDRk"
      },
      {
        "external_urls": {
          "spotify": "https://open.spotify.com/artist/2NHT2PJ2UmOu6Y6Wj73imp"
        },
        "href": "https://api.spotify.com/v1/artists/2NHT2PJ2UmOu6Y6Wj73imp",
        "id": "2NHT2PJ2UmOu6Y6Wj73imp",
        "name": "Betty White",
        "type": "artist",
        "uri": "spotify:artist:2NHT2PJ2UmOu6Y6Wj73imp"
      },
      {
        "external_urls": {
          "spotify": "https://open.spotify.com/artist/4OvBaBOYjyftit2jET0z5O"
        },
        "href": "https://api.spotify.com/v1/artists/4OvBaBOYjyftit2jET0z5O",
        "id": "4OvBaBOYjyftit2jET0z5O",
        "name": "Rob Riggle",
        "type": "artist",
        "uri": "spotify:artist:4OvBaBOYjyftit2jET0z5O"
      }
    ],
    "disc_number": 1,
    "duration_ms": 197813,
    "explicit": false,
    "external_urls": {
      "spotify": "https://open.spotify.com/track/4SkLlx52MxuRhFBbqE2Fgx"
    },
    "href": "https://api.spotify.com/v1/tracks/4SkLlx52MxuRhFBbqE2Fgx",
    "id": "4SkLlx52MxuRhFBbqE2Fgx",
    "name": "Let It Grow - From \"Dr. Seuss' The Lorax\"",
    "track_number": 14,
    "type": "track",
    "uri": "spotify:track:4SkLlx52MxuRhFBbqE2Fgx",
    "is_local": false
  },
  {
    "artists": [
      {
        "external_urls": {
          "spotify": "https://open.spotify.com/artist/0SrIPejckovMwhrN3MZFPB"
        },
        "href": "https://api.spotify.com/v1/artists/0SrIPejckovMwhrN3MZFPB",
        "id": "0SrIPejckovMwhrN3MZFPB",
        "name": "Daisy the Great",
        "type": "artist",
        "uri": "spotify:artist:0SrIPejckovMwhrN3MZFPB"
      },
      {
        "external_urls": {
          "spotify": "https://open.spotify.com/artist/6s22t5Y3prQHyaHWUN1R1C"
        },
        "href": "https://api.spotify.com/v1/artists/6s22t5Y3prQHyaHWUN1R1C",
        "id": "6s22t5Y3prQHyaHWUN1R1C",
        "name": "AJR",
        "type": "artist",
        "uri": "spotify:artist:6s22t5Y3prQHyaHWUN1R1C"
      }
    ],
    "disc_number": 1,
    "duration_ms": 149538,
    "explicit": false,
    "external_urls": {
      "spotify": "https://open.spotify.com/track/5DgsVfRlh4OrjzrrKZK0yq"
    },
    "href": "https://api.spotify.com/v1/tracks/5DgsVfRlh4OrjzrrKZK0yq",
    "id": "5DgsVfRlh4OrjzrrKZK0yq",
    "name": "Record Player",
    "track_number": 15,
    "type": "track",
    "uri": "spotify:track:5DgsVfRlh4OrjzrrKZK0yq",
    "is_local": false
  },
  {
    "artists": [
      {
        "external_urls": {
          "spotify": "https://open.spotify.com/artist/1uNFoZAHBGtllmzznpCI3s"
        },
        "href": "https://api.spotify.com/v1/artists/1uNFoZAHBGtllmzznpCI3s",
        "id": "1uNFoZAHBGtllmzznpCI3s",
        "name": "Justin Bieber",
        "type": "artist",
        "uri": "spotify:artist:1uNFoZAHBGtllmzznpCI3s"
      }
    ],
    "disc_number": 1,
    "duration_ms": 208542,
    "explicit": false,
    "external_urls": {
      "spotify": "https://open.spotify.com/track/7D7qsbLjvemHXVoMHIuwNI"
    },
    "href": "https://api.spotify.com/v1/tracks/7D7qsbLjvemHXVoMHIuwNI",
    "id": "7D7qsbLjvemHXVoMHIuwNI",
    "name": "What Do You Mean?",
    "track_number": 16,
    "type": "track",
    "uri": "spotify:track:7D7qsbLjvemHXVoMHIuwNI",
    "is_local": false
  },
  {
    "artists": [
      {
        "external_urls": {
          "spotify": "https://open.spotify.com/artist/6jJ0s89eD6GaHleKKya26X"
        },
        "href": "https://api.spotify.com/v1/artists/6jJ0s89eD6GaHleKKya26X",
        "id": "6jJ0s89eD6GaHleKKya26X",
        "name": "Katy Perry",
        "type": "artist",
        "uri": "spotify:artist:6jJ0s89eD6GaHleKKya26X"
      }
    ],
    "disc_number": 1,
    "duration_ms": 185481,
    "explicit": false,
    "external_urls": {
      "spotify": "https://open.spotify.com/track/5mSZlPQziaKXguCYY5CKi9"
    },
    "href": "https://api.spotify.com/v1/tracks/5mSZlPQziaKXguCYY5CKi9",
    "id": "5mSZlPQziaKXguCYY5CKi9",
    "name": "Harleys In Hawaii",
    "track_number": 17,
    "type": "track",
    "uri": "spotify:track:5mSZlPQziaKXguCYY5CKi9",
    "is_local": false
  },
  {
    "artists": [
      {
        "external_urls": {
          "spotify": "https://open.spotify.com/artist/49HlOY4gkHqsYG9GCuhkcc"
        },
        "href": "https://api.spotify.com/v1/artists/49HlOY4gkHqsYG9GCuhkcc",
        "id": "49HlOY4gkHqsYG9GCuhkcc",
        "name": "Celeste",
        "type": "artist",
        "uri": "spotify:artist:49HlOY4gkHqsYG9GCuhkcc"
      }
    ],
    "disc_number": 1,
    "duration_ms": 255986,
    "explicit": false,
    "external_urls": {
      "spotify": "https://open.spotify.com/track/42x9JnkzgaeiVuscYvbOyT"
    },
    "href": "https://api.spotify.com/v1/tracks/42x9JnkzgaeiVuscYvbOyT",
    "id": "42x9JnkzgaeiVuscYvbOyT",
    "name": "Strange",
    "track_number": 18,
    "type": "track",
    "uri": "spotify:track:42x9JnkzgaeiVuscYvbOyT",
    "is_local": false
  },
  {
    "artists": [
      {
        "external_urls": {
          "spotify": "https://open.spotify.com/artist/6TIYQ3jFPwQSRmorSezPxX"
        },
        "href": "https://api.spotify.com/v1/artists/6TIYQ3jFPwQSRmorSezPxX",
        "id": "6TIYQ3jFPwQSRmorSezPxX",
        "name": "mgk",
        "type": "artist",
        "uri": "spotify:artist:6TIYQ3jFPwQSRmorSezPxX"
      }
    ],
    "disc_number": 1,
    "duration_ms": 180370,
    "explicit": true,
    "external_urls": {
      "spotify": "https://open.spotify.com/track/0ZDbhaSZ0itRjDTa1DSJQf"
    },
    "href": "https://api.spotify.com/v1/tracks/0ZDbhaSZ0itRjDTa1DSJQf",
    "id": "0ZDbhaSZ0itRjDTa1DSJQf",
    "name": "papercuts",
    "track_number": 19,
    "type": "track",
    "uri": "spotify:track:0ZDbhaSZ0itRjDTa1DSJQf",
    "is_local": false
  },
  {
    "artists": [
      {
        "external_urls": {
          "spotify": "https://open.spotify.com/artist/06HL4z0CvFAxyc27GXpf02"
        },
        "href": "https://api.spotify.com/v1/artists/06HL4z0CvFAxyc27GXpf02",
        "id": "06HL4z0CvFAxyc27GXpf02",
        "name": "Taylor Swift",
        "type": "artist",
        "uri": "spotify:artist:06HL4z0CvFAxyc27GXpf02"
      }
    ],
    "disc_number": 1,
    "duration_ms": 239560,
    "explicit": false,
    "external_urls": {
      "spotify": "https://open.spotify.com/track/1ARwzIOdV8aEh7tllTDwm0"
    },
    "href": "https://api.spotify.com/v1/tracks/1ARwzIOdV8aEh7tllTDwm0",
    "id": "1ARwzIOdV8aEh7tllTDwm0",
    "name": "cardigan",
    "track_number": 20,
    "type": "track",
    "uri": "spotify:track:1ARwzIOdV8aEh7tllTDwm0",
    "is_local": false
  },
  {
    "artists": [
      {
        "external_urls": {
          "spotify": "https://open.spotify.com/artist/1moxjboGR7GNWYIMWsRjgG"
        },
        "href": "https://api.spotify.com/v1/artists/1moxjboGR7GNWYIMWsRjgG",
        "id": "1moxjboGR7GNWYIMWsRjgG",
        "name": "Florence + The Machine",
        "type": "artist",
        "uri": "spotify:artist:1moxjboGR7GNWYIMWsRjgG"
      }
    ],
    "disc_number": 1,
    "duration_ms": 252853,
    "explicit": false,
    "external_urls": {
      "spotify": "https://open.spotify.com/track/6lD9K3UGMOVxl0KwdRjmox"
    },
    "href": "https://api.spotify.com/v1/tracks/6lD9K3UGMOVxl0KwdRjmox",
    "id": "6lD9K3UGMOVxl0KwdRjmox",
    "name": "Dog Days Are Over",
    "track_number": 21,
    "type": "track",
    "uri": "spotify:track:6lD9K3UGMOVxl0KwdRjmox",
    "is_local": false
  },
  {
    "artists": [
      {
        "external_urls": {
          "spotify": "https://open.spotify.com/artist/08b2PA6eFyugsWAk41eQKZ"
        },
        "href": "https://api.spotify.com/v1/artists/08b2PA6eFyugsWAk41eQKZ",
        "id": "08b2PA6eFyugsWAk41eQKZ",
        "name": "Lesley Gore",
        "type": "artist",
        "uri": "spotify:artist:08b2PA6eFyugsWAk41eQKZ"
      }
    ],
    "disc_number": 1,
    "duration_ms": 142333,
    "explicit": false,
    "external_urls": {
      "spotify": "https://open.spotify.com/track/1pwu2dnK0OKkTMcoyGKgdq"
    },
    "href": "https://api.spotify.com/v1/tracks/1pwu2dnK0OKkTMcoyGKgdq",
    "id": "1pwu2dnK0OKkTMcoyGKgdq",
    "name": "It's My Party",
    "track_number": 22,
    "type": "track",
    "uri": "spotify:track:1pwu2dnK0OKkTMcoyGKgdq",
    "is_local": false
  },
  {
    "artists": [
      {
        "external_urls": {
          "spotify": "https://open.spotify.com/artist/0f2YkMXwFNJNSX7MymevKE"
        },
        "href": "https://api.spotify.com/v1/artists/0f2YkMXwFNJNSX7MymevKE",
        "id": "0f2YkMXwFNJNSX7MymevKE",
        "name": "Kaash Paige",
        "type": "artist",
        "uri": "spotify:artist:0f2YkMXwFNJNSX7MymevKE"
      }
    ],
    "disc_number": 1,
    "duration_ms": 148640,
    "explicit": false,
    "external_urls": {
      "spotify": "https://open.spotify.com/track/6bSeVVM9dH7xkgEpSJtBxP"
    },
    "href": "https://api.spotify.com/v1/tracks/6bSeVVM9dH7xkgEpSJtBxP",
    "id": "6bSeVVM9dH7xkgEpSJtBxP",
    "name": "Love Songs",
    "track_number": 23,
    "type": "track",
    "uri": "spotify:track:6bSeVVM9dH7xkgEpSJtBxP",
    "is_local": false
  },
  {
    "artists": [
      {
        "external_urls": {
          "spotify": "https://open.spotify.com/artist/06HL4z0CvFAxyc27GXpf02"
        },
        "href": "https://api.spotify.com/v1/artists/06HL4z0CvFAxyc27GXpf02",
        "id": "06HL4z0CvFAxyc27GXpf02",
        "name": "Taylor Swift",
        "type": "artist",
        "uri": "spotify:artist:06HL4z0CvFAxyc27GXpf02"
      }
    ],
    "disc_number": 1,
    "duration_ms": 214706,
    "explicit": false,
    "external_urls": {
      "spotify": "https://open.spotify.com/track/2EJg1huaq6HP20Hs9y8Vcb"
    },
    "href": "https://api.spotify.com/v1/tracks/2EJg1huaq6HP20Hs9y8Vcb",
    "id": "2EJg1huaq6HP20Hs9y8Vcb",
    "name": "willow",
    "track_number": 24,
    "type": "track",
    "uri": "spotify:track:2EJg1huaq6HP20Hs9y8Vcb",
    "is_local": false
  },
  {
    "artists": [
      {
        "external_urls": {
          "spotify": "https://open.spotify.com/artist/49YbNTLaaAbZHLtDI2aPGL"
        },
        "href": "https://api.spotify.com/v1/artists/49YbNTLaaAbZHLtDI2aPGL",
        "id": "49YbNTLaaAbZHLtDI2aPGL",
        "name": "Tesher",
        "type": "artist",
        "uri": "spotify:artist:49YbNTLaaAbZHLtDI2aPGL"
      },
      {
        "external_urls": {
          "spotify": "https://open.spotify.com/artist/07YZf4WDAMNwqr4jfgOZ8y"
        },
        "href": "https://api.spotify.com/v1/artists/07YZf4WDAMNwqr4jfgOZ8y",
        "id": "07YZf4WDAMNwqr4jfgOZ8y",
        "name": "Jason Derulo",
        "type": "artist",
        "uri": "spotify:artist:07YZf4WDAMNwqr4jfgOZ8y"
      }
    ],
    "disc_number": 1,
    "duration_ms": 169154,
    "explicit": true,
    "external_urls": {
      "spotify": "https://open.spotify.com/track/3PLEbgmbORh2kg8Xf8bTeE"
    },
    "href": "https://api.spotify.com/v1/tracks/3PLEbgmbORh2kg8Xf8bTeE",
    "id": "3PLEbgmbORh2kg8Xf8bTeE",
    "name": "Jalebi Baby",
    "track_number": 25,
    "type": "track",
    "uri": "spotify:track:3PLEbgmbORh2kg8Xf8bTeE",
    "is_local": false
  },
  {
    "artists": [
      {
        "external_urls": {
          "spotify": "https://open.spotify.com/artist/5rkVyNGXEgeUqKkB5ccK83"
        },
        "href": "https://api.spotify.com/v1/artists/5rkVyNGXEgeUqKkB5ccK83",
        "id": "5rkVyNGXEgeUqKkB5ccK83",
        "name": "Ashanti",
        "type": "artist",
        "uri": "spotify:artist:5rkVyNGXEgeUqKkB5ccK83"
      }
    ],
    "disc_number": 1,
    "duration_ms": 232293,
    "explicit": true,
    "external_urls": {
      "spotify": "https://open.spotify.com/track/3byTIur6ReBnOx1dMEni71"
    },
    "href": "https://api.spotify.com/v1/tracks/3byTIur6ReBnOx1dMEni71",
    "id": "3byTIur6ReBnOx1dMEni71",
    "name": "Foolish",
    "track_number": 26,
    "type": "track",
    "uri": "spotify:track:3byTIur6ReBnOx1dMEni71",
    "is_local": false
  },
  {
    "artists": [
      {
        "external_urls": {
          "spotify": "https://open.spotify.com/artist/6liAMWkVf5LH7YR9yfFy1Y"
        },
        "href": "https://api.spotify.com/v1/artists/6liAMWkVf5LH7YR9yfFy1Y",
        "id": "6liAMWkVf5LH7YR9yfFy1Y",
        "name": "Portishead",
        "type": "artist",
        "uri": "spotify:artist:6liAMWkVf5LH7YR9yfFy1Y"
      }
    ],
    "disc_number": 1,
    "duration_ms": 308626,
    "explicit": false,
    "external_urls": {
      "spotify": "https://open.spotify.com/track/5lYVrpKKbdpck93cDpUjEQ"
    },
    "href": "https://api.spotify.com/v1/tracks/5lYVrpKKbdpck93cDpUjEQ",
    "id": "5lYVrpKKbdpck93cDpUjEQ",
    "name": "Glory Box",
    "track_number": 27,
    "type": "track",
    "uri": "spotify:track:5lYVrpKKbdpck93cDpUjEQ",
    "is_local": false
  },
  {
    "artists": [
      {
        "external_urls": {
          "spotify": "https://open.spotify.com/artist/699OTQXzgjhIYAHMy9RyPD"
        },
        "href": "https://api.spotify.com/v1/artists/699OTQXzgjhIYAHMy9RyPD",
        "id": "699OTQXzgjhIYAHMy9RyPD",
        "name": "Playboi Carti",
        "type": "artist",
        "uri": "spotify:artist:699OTQXzgjhIYAHMy9RyPD"
      },
      {
        "external_urls": {
          "spotify": "https://open.spotify.com/artist/2EMAnMvWE2eb56ToJVfCWs"
        },
        "href": "https://api.spotify.com/v1/artists/2EMAnMvWE2eb56ToJVfCWs",
        "id": "2EMAnMvWE2eb56ToJVfCWs",
        "name": "Bryson Tiller",
        "type": "artist",
        "uri": "spotify:artist:2EMAnMvWE2eb56ToJVfCWs"
      }
    ],
    "disc_number": 1,
    "duration_ms": 206333,
    "explicit": true,
    "external_urls": {
      "spotify": "https://open.spotify.com/track/0ZmDVojDNoJCAM57UEOoQl"
    },
    "href": "https://api.spotify.com/v1/tracks/0ZmDVojDNoJCAM57UEOoQl",
    "id": "0ZmDVojDNoJCAM57UEOoQl",
    "name": "Fell In Luv",
    "track_number": 28,
    "type": "track",
    "uri": "spotify:track:0ZmDVojDNoJCAM57UEOoQl",
    "is_local": false
  },
  {
    "artists": [
      {
        "external_urls": {
          "spotify": "https://open.spotify.com/artist/0X2BH1fck6amBIoJhDVmmJ"
        },
        "href": "https://api.spotify.com/v1/artists/0X2BH1fck6amBIoJhDVmmJ",
        "id": "0X2BH1fck6amBIoJhDVmmJ",
        "name": "Ellie Goulding",
        "type": "artist",
        "uri": "spotify:artist:0X2BH1fck6amBIoJhDVmmJ"
      }
    ],
    "disc_number": 1,
    "duration_ms": 240867,
    "explicit": false,
    "external_urls": {
      "spotify": "https://open.spotify.com/track/4XlzYCZazPlifqOFaI9oAJ"
    },
    "href": "https://api.spotify.com/v1/tracks/4XlzYCZazPlifqOFaI9oAJ",
    "id": "4XlzYCZazPlifqOFaI9oAJ",
    "name": "Still Falling For You - From \"Bridget Jones's Baby\"",
    "track_number": 29,
    "type": "track",
    "uri": "spotify:track:4XlzYCZazPlifqOFaI9oAJ",
    "is_local": false
  },
  {
    "artists": [
      {
        "external_urls": {
          "spotify": "https://open.spotify.com/artist/06HL4z0CvFAxyc27GXpf02"
        },
        "href": "https://api.spotify.com/v1/artists/06HL4z0CvFAxyc27GXpf02",
        "id": "06HL4z0CvFAxyc27GXpf02",
        "name": "Taylor Swift",
        "type": "artist",
        "uri": "spotify:artist:06HL4z0CvFAxyc27GXpf02"
      }
    ],
    "disc_number": 1,
    "duration_ms": 235766,
    "explicit": false,
    "external_urls": {
      "spotify": "https://open.spotify.com/track/0VVYjOFcExPOU7e6PHxEYq"
    },
    "href": "https://api.spotify.com/v1/tracks/0VVYjOFcExPOU7e6PHxEYq",
    "id": "0VVYjOFcExPOU7e6PHxEYq",
    "name": "Love Story (Taylor’s Version)",
    "track_number": 30,
    "type": "track",
    "uri": "spotify:track:0VVYjOFcExPOU7e6PHxEYq",
    "is_local": false
  },
  {
    "artists": [
      {
        "external_urls": {
          "spotify": "https://open.spotify.com/artist/2rGm8R7YDTbqDCVlNssQyL"
        },
        "href": "https://api.spotify.com/v1/artists/2rGm8R7YDTbqDCVlNssQyL",
        "id": "2rGm8R7YDTbqDCVlNssQyL",
        "name": "DNA",
        "type": "artist",
        "uri": "spotify:artist:2rGm8R7YDTbqDCVlNssQyL"
      },
      {
        "external_urls": {
          "spotify": "https://open.spotify.com/artist/3X0tJzVYoWlfjLYI0Ridsw"
        },
        "href": "https://api.spotify.com/v1/artists/3X0tJzVYoWlfjLYI0Ridsw",
        "id": "3X0tJzVYoWlfjLYI0Ridsw",
        "name": "Suzanne Vega",
        "type": "artist",
        "uri": "spotify:artist:3X0tJzVYoWlfjLYI0Ridsw"
      }
    ],
    "disc_number": 1,
    "duration_ms": 326066,
    "explicit": false,
    "external_urls": {
      "spotify": "https://open.spotify.com/track/4QaIEJRHcnwdfCUUkLgZID"
    },
    "href": "https://api.spotify.com/v1/tracks/4QaIEJRHcnwdfCUUkLgZID",
    "id": "4QaIEJRHcnwdfCUUkLgZID",
    "name": "Tom's Diner",
    "track_number": 31,
    "type": "track",
    "uri": "spotify:track:4QaIEJRHcnwdfCUUkLgZID",
    "is_local": false
  },
  {
    "artists": [
      {
        "external_urls": {
          "spotify": "https://open.spotify.com/artist/4yiQZ8tQPux8cPriYMWUFP"
        },
        "href": "https://api.spotify.com/v1/artists/4yiQZ8tQPux8cPriYMWUFP",
        "id": "4yiQZ8tQPux8cPriYMWUFP",
        "name": "Gwen Stefani",
        "type": "artist",
        "uri": "spotify:artist:4yiQZ8tQPux8cPriYMWUFP"
      }
    ],
    "disc_number": 1,
    "duration_ms": 264920,
    "explicit": false,
    "external_urls": {
      "spotify": "https://open.spotify.com/track/7Aqxwfh3aNYwrP3Y9WCeJL"
    },
    "href": "https://api.spotify.com/v1/tracks/7Aqxwfh3aNYwrP3Y9WCeJL",
    "id": "7Aqxwfh3aNYwrP3Y9WCeJL",
    "name": "Luxurious",
    "track_number": 32,
    "type": "track",
    "uri": "spotify:track:7Aqxwfh3aNYwrP3Y9WCeJL",
    "is_local": false
  },
  {
    "artists": [
      {
        "external_urls": {
          "spotify": "https://open.spotify.com/artist/06HL4z0CvFAxyc27GXpf02"
        },
        "href": "https://api.spotify.com/v1/artists/06HL4z0CvFAxyc27GXpf02",
        "id": "06HL4z0CvFAxyc27GXpf02",
        "name": "Taylor Swift",
        "type": "artist",
        "uri": "spotify:artist:06HL4z0CvFAxyc27GXpf02"
      }
    ],
    "disc_number": 1,
    "duration_ms": 231124,
    "explicit": false,
    "external_urls": {
      "spotify": "https://open.spotify.com/track/07mCT6Txu7DYKBMp3hzNjy"
    },
    "href": "https://api.spotify.com/v1/tracks/07mCT6Txu7DYKBMp3hzNjy",
    "id": "07mCT6Txu7DYKBMp3hzNjy",
    "name": "You Belong With Me (Taylor’s Version)",
    "track_number": 33,
    "type": "track",
    "uri": "spotify:track:07mCT6Txu7DYKBMp3hzNjy",
    "is_local": false
  },
  {
    "artists": [
      {
        "external_urls": {
          "spotify": "https://open.spotify.com/artist/4NpFxQe2UvRCAjto3JqlSl"
        },
        "href": "https://api.spotify.com/v1/artists/4NpFxQe2UvRCAjto3JqlSl",
        "id": "4NpFxQe2UvRCAjto3JqlSl",
        "name": "Greta Van Fleet",
        "type": "artist",
        "uri": "spotify:artist:4NpFxQe2UvRCAjto3JqlSl"
      }
    ],
    "disc_number": 1,
    "duration_ms": 266933,
    "explicit": false,
    "external_urls": {
      "spotify": "https://open.spotify.com/track/3s2FV1QCV83I2Nfrxeh3pQ"
    },
    "href": "https://api.spotify.com/v1/tracks/3s2FV1QCV83I2Nfrxeh3pQ",
    "id": "3s2FV1QCV83I2Nfrxeh3pQ",
    "name": "You're The One",
    "track_number": 34,
    "type": "track",
    "uri": "spotify:track:3s2FV1QCV83I2Nfrxeh3pQ",
    "is_local": false
  },
  {
    "artists": [
      {
        "external_urls": {
          "spotify": "https://open.spotify.com/artist/0QJIPDAEDILuo8AIq3pMuU"
        },
        "href": "https://api.spotify.com/v1/artists/0QJIPDAEDILuo8AIq3pMuU",
        "id": "0QJIPDAEDILuo8AIq3pMuU",
        "name": "M.I.A.",
        "type": "artist",
        "uri": "spotify:artist:0QJIPDAEDILuo8AIq3pMuU"
      }
    ],
    "disc_number": 1,
    "duration_ms": 227520,
    "explicit": false,
    "external_urls": {
      "spotify": "https://open.spotify.com/track/0pbRIaeRViFxcnUhwDsq4J"
    },
    "href": "https://api.spotify.com/v1/tracks/0pbRIaeRViFxcnUhwDsq4J",
    "id": "0pbRIaeRViFxcnUhwDsq4J",
    "name": "Bad Girls",
    "track_number": 35,
    "type": "track",
    "uri": "spotify:track:0pbRIaeRViFxcnUhwDsq4J",
    "is_local": false
  },
  {
    "artists": [
      {
        "external_urls": {
          "spotify": "https://open.spotify.com/artist/0LcJLqbBmaGUft1e9Mm8HV"
        },
        "href": "https://api.spotify.com/v1/artists/0LcJLqbBmaGUft1e9Mm8HV",
        "id": "0LcJLqbBmaGUft1e9Mm8HV",
        "name": "ABBA",
        "type": "artist",
        "uri": "spotify:artist:0LcJLqbBmaGUft1e9Mm8HV"
      }
    ],
    "disc_number": 1,
    "duration_ms": 325906,
    "explicit": false,
    "external_urls": {
      "spotify": "https://open.spotify.com/track/6u8rdt398PVA4pyrB4gYjb"
    },
    "href": "https://api.spotify.com/v1/tracks/6u8rdt398PVA4pyrB4gYjb",
    "id": "6u8rdt398PVA4pyrB4gYjb",
    "name": "Chiquitita",
    "track_number": 36,
    "type": "track",
    "uri": "spotify:track:6u8rdt398PVA4pyrB4gYjb",
    "is_local": false
  },
  {
    "artists": [
      {
        "external_urls": {
          "spotify": "https://open.spotify.com/artist/5ZS223C6JyBfXasXxrRqOk"
        },
        "href": "https://api.spotify.com/v1/artists/5ZS223C6JyBfXasXxrRqOk",
        "id": "5ZS223C6JyBfXasXxrRqOk",
        "name": "Jhené Aiko",
        "type": "artist",
        "uri": "spotify:artist:5ZS223C6JyBfXasXxrRqOk"
      }
    ],
    "disc_number": 1,
    "duration_ms": 239240,
    "explicit": false,
    "external_urls": {
      "spotify": "https://open.spotify.com/track/0W5Xi159Ys0JNEFLM2lYhK"
    },
    "href": "https://api.spotify.com/v1/tracks/0W5Xi159Ys0JNEFLM2lYhK",
    "id": "0W5Xi159Ys0JNEFLM2lYhK",
    "name": "W.A.Y.S.",
    "track_number": 37,
    "type": "track",
    "uri": "spotify:track:0W5Xi159Ys0JNEFLM2lYhK",
    "is_local": false
  },
  {
    "artists": [
      {
        "external_urls": {
          "spotify": "https://open.spotify.com/artist/4XQI4hyuy5xun1ou3SM8Oe"
        },
        "href": "https://api.spotify.com/v1/artists/4XQI4hyuy5xun1ou3SM8Oe",
        "id": "4XQI4hyuy5xun1ou3SM8Oe",
        "name": "Aidan Bissett",
        "type": "artist",
        "uri": "spotify:artist:4XQI4hyuy5xun1ou3SM8Oe"
      }
    ],
    "disc_number": 1,
    "duration_ms": 183012,
    "explicit": false,
    "external_urls": {
      "spotify": "https://open.spotify.com/track/1602N5oMDAguJu2n8UzMQe"
    },
    "href": "https://api.spotify.com/v1/tracks/1602N5oMDAguJu2n8UzMQe",
    "id": "1602N5oMDAguJu2n8UzMQe",
    "name": "More Than Friends",
    "track_number": 38,
    "type": "track",
    "uri": "spotify:track:1602N5oMDAguJu2n8UzMQe",
    "is_local": false
  },
  {
    "artists": [
      {
        "external_urls": {
          "spotify": "https://open.spotify.com/artist/5sWHDYs0csV6RS48xBl0tH"
        },
        "href": "https://api.spotify.com/v1/artists/5sWHDYs0csV6RS48xBl0tH",
        "id": "5sWHDYs0csV6RS48xBl0tH",
        "name": "Two Feet",
        "type": "artist",
        "uri": "spotify:artist:5sWHDYs0csV6RS48xBl0tH"
      }
    ],
    "disc_number": 1,
    "duration_ms": 185520,
    "explicit": false,
    "external_urls": {
      "spotify": "https://open.spotify.com/track/5cnCkyU15QomWUYaxj7Rcx"
    },
    "href": "https://api.spotify.com/v1/tracks/5cnCkyU15QomWUYaxj7Rcx",
    "id": "5cnCkyU15QomWUYaxj7Rcx",
    "name": "I Feel Like I'm Drowning",
    "track_number": 39,
    "type": "track",
    "uri": "spotify:track:5cnCkyU15QomWUYaxj7Rcx",
    "is_local": false
  }
]